odoo/addons/l10n_it_fiscalcode_sale/README.rst
odoo/addons/l10n_it_fiscalcode_sale/__init__.py
odoo/addons/l10n_it_fiscalcode_sale/__manifest__.py
odoo/addons/l10n_it_fiscalcode_sale/i18n/it.po
odoo/addons/l10n_it_fiscalcode_sale/i18n/l10n_it_fiscalcode_sale.pot
odoo/addons/l10n_it_fiscalcode_sale/readme/CONTRIBUTORS.rst
odoo/addons/l10n_it_fiscalcode_sale/readme/DESCRIPTION.rst
odoo/addons/l10n_it_fiscalcode_sale/static/description/icon.png
odoo/addons/l10n_it_fiscalcode_sale/static/description/index.html
odoo/addons/l10n_it_fiscalcode_sale/views/sale_order_report.xml
odoo12_addon_l10n_it_fiscalcode_sale-12.0.1.0.1.dist-info/METADATA
odoo12_addon_l10n_it_fiscalcode_sale-12.0.1.0.1.dist-info/WHEEL
odoo12_addon_l10n_it_fiscalcode_sale-12.0.1.0.1.dist-info/top_level.txt
odoo12_addon_l10n_it_fiscalcode_sale-12.0.1.0.1.dist-info/RECORD
